README.rst
setup.py
pyquchk/__init__.py
pyquchk/checker.py
pyquchk/lazylist.py
pyquchk/qc_decorator.py
pyquchk/utils.py
pyquchk.egg-info/PKG-INFO
pyquchk.egg-info/SOURCES.txt
pyquchk.egg-info/dependency_links.txt
pyquchk.egg-info/requires.txt
pyquchk.egg-info/top_level.txt
pyquchk/arbitraries/__init__.py
pyquchk/arbitraries/arbitrary.py
pyquchk/arbitraries/numbers.py
pyquchk/arbitraries/primitives.py
pyquchk/arbitraries/sequences.py
pyquchk/arbitraries/utils.py
tests/__init__.py
tests/test_basic.py
tests/test_forall.py